isaura/__init__.py
isaura/blocs/__init__.py
isaura/blocs/precalc.py
isaura/core/__init__.py
isaura/core/api.py
isaura/core/base.py
isaura/core/hdf5.py
isaura/default.py
isaura/dtypes/__init__.py
isaura/dtypes/numeric.py
isaura/handle/__init__.py
isaura/handle/appender.py
isaura/handle/io.py
isaura/handle/mapper.py
isaura/handle/reader.py
isaura/handle/remove.py
isaura/handle/repacker.py
isaura/handle/retyper.py
isaura/handle/writer.py
isaura/iac/__init__.py
isaura/iac/aws_precalc_stack.py
isaura/local/__init__.py
isaura/local/mixins.py
isaura/local/models.py
isaura/routes/__init__.py
isaura/routes/precalc/__init__.py
isaura/routes/precalc/get/__init__.py
isaura/routes/precalc/get/app/__init__.py
isaura/routes/precalc/get/app/handler.py
isaura/routes/precalc/get/app/schema.py
isaura/routes/schemas/__init__.py
isaura/routes/schemas/common.py
isaura/routes/status/__init__.py
isaura/routes/status/get/__init__.py
isaura/routes/status/get/app/__init__.py
isaura/routes/status/get/app/handler.py
isaura/service/__init__.py
isaura/service/client.py
isaura/utils/__init__.py
isaura/utils/aws.py
isaura/utils/dirs.py
isaura/utils/logging.py
isaura-0.18.0.dist-info/METADATA
isaura-0.18.0.dist-info/WHEEL
isaura-0.18.0.dist-info/LICENSE
isaura-0.18.0.dist-info/RECORD
